issue_assistant/__init__.py
issue_assistant/artifacts.py
issue_assistant/automation.py
issue_assistant/cli.py
issue_assistant/github.py
issue_assistant/models.py
issue_assistant/phase_registry.py
issue_assistant/phases.py
issue_assistant/pipeline.py
issue_assistant/phases/__init__.py
issue_assistant/phases/actions.py
issue_assistant/phases/contributor_guide.py
issue_assistant/phases/dependencies.py
issue_assistant/phases/duplicates.py
issue_assistant/phases/duplicates_baseline.py
issue_assistant/phases/explainability.py
issue_assistant/phases/issue_health.py
issue_assistant/phases/knowledge_base.py
issue_assistant/phases/labels.py
issue_assistant/phases/lifecycle.py
issue_assistant/phases/low_signal.py
issue_assistant/phases/maintainer_cost.py
issue_assistant/phases/maintainer_load.py
issue_assistant/phases/normalization.py
issue_assistant/phases/playbooks.py
issue_assistant/phases/quality_breakdown.py
issue_assistant/phases/quality_heuristics.py
issue_assistant/phases/triage.py
issue_assistant/phases/weekly_digest.py
issue_assistant-0.2.1.dist-info/licenses/LICENSE
issue_assistant-0.2.1.dist-info/METADATA
issue_assistant-0.2.1.dist-info/WHEEL
issue_assistant-0.2.1.dist-info/entry_points.txt
issue_assistant-0.2.1.dist-info/top_level.txt
issue_assistant-0.2.1.dist-info/RECORD
