Metadata-Version: 2.4
Name: issue-assistant
Version: 0.2.1
Summary: Deterministic-first GitHub issue triage engine
License: MIT License
Requires-Python: >=3.10
License-File: LICENSE
Requires-Dist: requests>=2.31.0
Provides-Extra: dev
Requires-Dist: pytest>=7.0.0; extra == "dev"
Dynamic: license-file
